elkar/__init__.py
elkar/a2a_errors.py
elkar/a2a_orchestrator_mcp.py
elkar/a2a_types.py
elkar/common.py
elkar/json_rpc.py
elkar/py.typed
elkar/api_client/__init__.py
elkar/api_client/client.py
elkar/api_client/models.py
elkar/client/__init__.py
elkar/client/a2a_client.py
elkar/client/base.py
elkar/client/client_task_manager.py
elkar/server/__init__.py
elkar/server/server.py
elkar/store/__init__.py
elkar/store/base.py
elkar/store/elkar_client_store.py
elkar/store/in_memory.py
elkar/task_manager/__init__.py
elkar/task_manager/task_manager_base.py
elkar/task_manager/task_manager_with_store.py
elkar/task_manager/task_manager_with_task_modifier.py
elkar/task_modifier/__init__.py
elkar/task_modifier/base.py
elkar/task_modifier/task_modifier.py
elkar/task_queue/__init__.py
elkar/task_queue/base.py
elkar/task_queue/elkar_client_queue.py
elkar/task_queue/in_memory.py
elkar-0.1.23.dist-info/METADATA
elkar-0.1.23.dist-info/WHEEL
elkar-0.1.23.dist-info/licenses/LICENCE
elkar-0.1.23.dist-info/RECORD
