Metadata-Version: 2.4
Name: elkar
Version: 0.1.23
Summary: The open-source protocol to send, track, and orchestrate tasks between AI agents
Project-URL: Homepage, https://www.elkar.co
Project-URL: Documentation, https://docs.elkar.co
Project-URL: Repository, https://github.com/elkar-ai/elkar-a2a
Project-URL: Issues, https://github.com/elkar-ai/elkar-a2a/issues
Author-email: Laurent Meunier <laurent@breezyai.co>
License-Expression: MIT
License-File: LICENCE
Classifier: Development Status :: 4 - Beta
Classifier: Intended Audience :: Developers
Classifier: License :: OSI Approved :: MIT License
Classifier: Programming Language :: Python :: 3
Classifier: Programming Language :: Python :: 3.12
Classifier: Topic :: Software Development :: Libraries :: Python Modules
Classifier: Typing :: Typed
Requires-Python: >=3.10
Requires-Dist: aiohttp>=3.11.18
Requires-Dist: colorlog>=6.9.0
Requires-Dist: fastapi
Requires-Dist: mcp>=1.7.0
Requires-Dist: pre-commit>=4.2.0
Requires-Dist: psycopg>=3.2.7
Requires-Dist: pydantic
Requires-Dist: pyjwt>=2.10.1
Requires-Dist: requests>=2.32.3
Requires-Dist: sqlalchemy>=2.0.40
Requires-Dist: sse-starlette>=2.3.3
Requires-Dist: starlette>=0.46.2
Requires-Dist: supabase>=2.15.1
Requires-Dist: uvicorn>=0.34.2
